helldivepy/__init__.py
helldivepy/api/__init__.py
helldivepy/api/assignments.py
helldivepy/api/base.py
helldivepy/api/campaigns.py
helldivepy/api/dispatches.py
helldivepy/api/planets.py
helldivepy/api/space_stations.py
helldivepy/api/steam.py
helldivepy/api/war.py
helldivepy/api_client.py
helldivepy/constants.py
helldivepy/enums.py
helldivepy/models.py
helldivepy/utils.py
helldivepy-0.1.1.dist-info/LICENSE
helldivepy-0.1.1.dist-info/METADATA
helldivepy-0.1.1.dist-info/WHEEL
helldivepy-0.1.1.dist-info/RECORD
