Metadata-Version: 2.1
Name: helldivepy
Version: 0.1.1
Summary: A Helldivers 2 API wrapper using the Diveharder API and the Helldivers Community API
License: MIT
Keywords: helldivers 2,api,wrapper,diveharder,community
Author: AJXD2
Author-email: aj@ajxd2.dev
Requires-Python: >=3.11,<4.0
Classifier: Intended Audience :: Developers
Classifier: License :: OSI Approved :: MIT License
Classifier: Programming Language :: Python :: 3
Classifier: Programming Language :: Python :: 3.11
Classifier: Programming Language :: Python :: 3.12
Classifier: Programming Language :: Python :: 3.13
Classifier: Topic :: Games/Entertainment
Classifier: Topic :: System :: Networking
Classifier: Typing :: Typed
Requires-Dist: fire (>=0.7.0,<0.8.0)
Requires-Dist: pydantic (>=2.10.3,<3.0.0)
Requires-Dist: requests (>=2.32.3,<3.0.0)
Requires-Dist: rich (>=13.9.4,<14.0.0)
Project-URL: documentation, https://github.com/ajxd2/helldive.py#readme
Project-URL: homepage, https://github.com/ajxd2/helldive.py
Project-URL: repository, https://github.com/ajxd2/helldive.py
